mictrack.py
mictrack-1.0.1.dist-info/METADATA
mictrack-1.0.1.dist-info/WHEEL
mictrack-1.0.1.dist-info/entry_points.txt
mictrack-1.0.1.dist-info/top_level.txt
mictrack-1.0.1.dist-info/RECORD
