Metadata-Version: 2.4
Name: mictrack
Version: 1.0.1
Requires-Dist: pydantic==2.12.5
Requires-Dist: pyserial==3.5
Requires-Dist: PyYAML==6.0.3
Provides-Extra: dev
Requires-Dist: types-pyserial==3.5.0; extra == "dev"
Requires-Dist: types-PyYAML==6.0.12; extra == "dev"
